deepreasoningwithtools/__init__.py
deepreasoningwithtools/cli.py
deepreasoningwithtools/import_utils.py
deepreasoningwithtools/records.py
deepreasoningwithtools/samplers/__init__.py
deepreasoningwithtools/samplers/abstract.py
deepreasoningwithtools/samplers/litellm_sampler.py
deepreasoningwithtools/samplers/vllm/sampler.py
deepreasoningwithtools/samplers/vllm/test_vllm.py
deepreasoningwithtools/samplers/vllm/vllm_client.py
deepreasoningwithtools/samplers/vllm/vllm_server.py
deepreasoningwithtools/test_modal_toolcaller.py
deepreasoningwithtools/test_toolcaller.py
deepreasoningwithtools/toolcaller.py
deepreasoningwithtools/tools/newsapi_tool.py
deepreasoningwithtools/tools/yfinance_tools.py
deepreasoningwithtools/utils.py
deepreasoningwithtools-0.1.6.dist-info/entry_points.txt
deepreasoningwithtools-0.1.6.dist-info/METADATA
deepreasoningwithtools-0.1.6.dist-info/WHEEL
deepreasoningwithtools-0.1.6.dist-info/RECORD
