Metadata-Version: 2.3
Name: deepreasoningwithtools
Version: 0.1.6
Summary: A package to inject python execution into the reasoning trace of LLMs.
License: MIT
Keywords: llm,reasoning,tools,python,ai
Author: Lukas
Author-email: lukas@nelsoftware.com
Requires-Python: >=3.11
Classifier: Development Status :: 4 - Beta
Classifier: Intended Audience :: Developers
Classifier: License :: OSI Approved :: MIT License
Classifier: Programming Language :: Python :: 3.12
Classifier: Topic :: Software Development :: Libraries :: Python Modules
Classifier: Topic :: Scientific/Engineering :: Artificial Intelligence
Provides-Extra: litellm
Provides-Extra: vllm
Requires-Dist: accelerate (>=1.6.0,<2.0.0)
Requires-Dist: bitsandbytes (>=0.45.5,<0.46.0) ; extra == "vllm"
Requires-Dist: datasets (>=3.5.0,<4.0.0)
Requires-Dist: fastapi (>=0.115.12,<0.116.0) ; extra == "vllm"
Requires-Dist: flashinfer-python ; extra == "vllm"
Requires-Dist: litellm (>=1.67.1,<2.0.0) ; extra == "litellm"
Requires-Dist: pydantic (>=2.11.3,<3.0.0)
Requires-Dist: requests (>=2.32.3,<3.0.0)
Requires-Dist: smolagents (>=1.14.0,<2.0.0)
Requires-Dist: torch (==2.6.0) ; extra == "vllm"
Requires-Dist: transformers (>=4.51.3,<5.0.0)
Requires-Dist: uvicorn (>=0.34.2,<0.35.0) ; extra == "vllm"
Requires-Dist: vllm (==0.8.3) ; extra == "vllm"
Requires-Dist: yfinance (>=0.2.56,<0.3.0)
Project-URL: Documentation, https://github.com/LukasNel/TRLLukas/tree/master/deeptools#readme
Project-URL: Homepage, https://github.com/LukasNel/TRLLukas/tree/master/deeptools
Project-URL: Repository, https://github.com/LukasNel/TRLLukas.git
